MANIFEST.in
MIT-LICENSE.txt
README.rst
requirements.txt
setup.py
django_frontend_notification.egg-info/PKG-INFO
django_frontend_notification.egg-info/SOURCES.txt
django_frontend_notification.egg-info/dependency_links.txt
django_frontend_notification.egg-info/not-zip-safe
django_frontend_notification.egg-info/requires.txt
django_frontend_notification.egg-info/top_level.txt
frontend_notification/__init__.py
frontend_notification/__init__.pyc
frontend_notification/constants.py
frontend_notification/forms.py
frontend_notification/tests.py
frontend_notification/urls.py
frontend_notification/views.py
frontend_notification/fixtures/notification.json
frontend_notification/locale/de/LC_MESSAGES/django.mo
frontend_notification/locale/de/LC_MESSAGES/django.po
frontend_notification/locale/en/LC_MESSAGES/django.mo
frontend_notification/locale/en/LC_MESSAGES/django.po
frontend_notification/locale/es/LC_MESSAGES/django.mo
frontend_notification/locale/es/LC_MESSAGES/django.po
frontend_notification/locale/fr/LC_MESSAGES/django.mo
frontend_notification/locale/fr/LC_MESSAGES/django.po
frontend_notification/locale/pt/LC_MESSAGES/django.mo
frontend_notification/locale/pt/LC_MESSAGES/django.po
frontend_notification/locale/ru/LC_MESSAGES/django.mo
frontend_notification/locale/ru/LC_MESSAGES/django.po
frontend_notification/templates/frontend/frontend_notification/user_notification.html
frontend_notification/templatetags/__init__.py
frontend_notification/templatetags/frontend_notification_tags.py