Metadata-Version: 1.1
Name: django-frontend-notification
Version: 1.0.4
Summary: django application to display list of notifications, run basic actions such as view all notifications and delete notifications
Home-page: http://github.com/areski/django-frontend-notification
Author: Belaid Arezqui
Author-email: areski@gmail.com
License: MIT License
Platform: UNKNOWN
Classifier: Development Status :: 5 - Production/Stable
Classifier: Environment :: Web Environment
Classifier: Framework :: Django
Classifier: Intended Audience :: Developers
Classifier: License :: OSI Approved :: MIT License
Classifier: Operating System :: OS Independent
Classifier: Programming Language :: Python
Classifier: Topic :: Software Development :: Libraries :: Python Modules
